_postgresql.pyd
pixeltable_pgserver/__init__.py
pixeltable_pgserver/_build.py
pixeltable_pgserver/_commands.py
pixeltable_pgserver/postgres_server.py
pixeltable_pgserver/py.typed
pixeltable_pgserver/utils.py
pixeltable_pgserver/pginstall/bin/clusterdb.exe
pixeltable_pgserver/pginstall/bin/createdb.exe
pixeltable_pgserver/pginstall/bin/createuser.exe
pixeltable_pgserver/pginstall/bin/dropdb.exe
pixeltable_pgserver/pginstall/bin/dropuser.exe
pixeltable_pgserver/pginstall/bin/ecpg.exe
pixeltable_pgserver/pginstall/bin/initdb.exe
pixeltable_pgserver/pginstall/bin/libecpg.dll
pixeltable_pgserver/pginstall/bin/libecpg_compat.dll
pixeltable_pgserver/pginstall/bin/libpgtypes.dll
pixeltable_pgserver/pginstall/bin/libpq.dll
pixeltable_pgserver/pginstall/bin/pg_amcheck.exe
pixeltable_pgserver/pginstall/bin/pg_archivecleanup.exe
pixeltable_pgserver/pginstall/bin/pg_basebackup.exe
pixeltable_pgserver/pginstall/bin/pg_checksums.exe
pixeltable_pgserver/pginstall/bin/pg_config.exe
pixeltable_pgserver/pginstall/bin/pg_controldata.exe
pixeltable_pgserver/pginstall/bin/pg_ctl.exe
pixeltable_pgserver/pginstall/bin/pg_dump.exe
pixeltable_pgserver/pginstall/bin/pg_dumpall.exe
pixeltable_pgserver/pginstall/bin/pg_isready.exe
pixeltable_pgserver/pginstall/bin/pg_receivewal.exe
pixeltable_pgserver/pginstall/bin/pg_recvlogical.exe
pixeltable_pgserver/pginstall/bin/pg_resetwal.exe
pixeltable_pgserver/pginstall/bin/pg_restore.exe
pixeltable_pgserver/pginstall/bin/pg_rewind.exe
pixeltable_pgserver/pginstall/bin/pg_test_fsync.exe
pixeltable_pgserver/pginstall/bin/pg_test_timing.exe
pixeltable_pgserver/pginstall/bin/pg_upgrade.exe
pixeltable_pgserver/pginstall/bin/pg_verifybackup.exe
pixeltable_pgserver/pginstall/bin/pg_waldump.exe
pixeltable_pgserver/pginstall/bin/pgbench.exe
pixeltable_pgserver/pginstall/bin/postgres.exe
pixeltable_pgserver/pginstall/bin/psql.exe
pixeltable_pgserver/pginstall/bin/reindexdb.exe
pixeltable_pgserver/pginstall/bin/vacuumdb.exe
pixeltable_pgserver-0.2.4.dist-info/LICENSE
pixeltable_pgserver-0.2.4.dist-info/METADATA
pixeltable_pgserver-0.2.4.dist-info/WHEEL
pixeltable_pgserver-0.2.4.dist-info/top_level.txt
pixeltable_pgserver-0.2.4.dist-info/RECORD
