Metadata-Version: 2.1
Name: pixeltable-pgserver
Version: 0.2.4
Summary: Embedded Postgres Server for Pixeltable
Author-email: "Pixeltable, Inc." <contact@pixeltable.com>
License: Apache License
Project-URL: repository, https://github.com/pixeltable/pixeltable-pgserver
Keywords: postgresql,pgvector,pgserver,pixeltable,rag
Requires-Python: >=3.9
License-File: LICENSE
Requires-Dist: fasteners>=0.19
Requires-Dist: platformdirs>=4.0.0
Requires-Dist: psutil>=5.9.0
Provides-Extra: dev
Requires-Dist: sysv-ipc; extra == "dev"
Provides-Extra: test
Requires-Dist: pytest; extra == "test"
Requires-Dist: psycopg2-binary; extra == "test"
Requires-Dist: sqlalchemy>=2; extra == "test"
Requires-Dist: sqlalchemy-utils; extra == "test"
